trino_query_parser/SqlBase.g4
trino_query_parser/SqlBaseLexer.py
trino_query_parser/SqlBaseListener.py
trino_query_parser/SqlBaseParser.py
trino_query_parser/SqlBaseVisitor.py
trino_query_parser/__init__.py
trino_query_parser/error.py
trino_query_parser/parser.py
trino_query_parser-0.422.7.dist-info/METADATA
trino_query_parser-0.422.7.dist-info/WHEEL
trino_query_parser-0.422.7.dist-info/top_level.txt
trino_query_parser-0.422.7.dist-info/RECORD
