Metadata-Version: 2.1
Name: trino-query-parser
Version: 0.422.7
Summary: Provides a parser for trino queries
Author-email: Gregory Borodin <grihabor@gmail.com>
License: Apache 2.0
Classifier: Programming Language :: Python :: 3.7
Classifier: Programming Language :: Python :: 3.8
Classifier: Programming Language :: Python :: 3.9
Classifier: Programming Language :: Python :: 3.10
Classifier: Programming Language :: Python :: 3.11
Requires-Dist: antlr4-python3-runtime (==4.13.0)
Provides-Extra: test
Requires-Dist: pytest ; extra == 'test'
